unictelecome
