Metadata-Version: 1.1
Name: unictelecomes
Version: 1.6.4
Summary: Send sms from unictelecome.
Home-page: https://github.com/SamirWardak/sendmessageunictelecome
Author: Wardak Ahmad Samir
Author-email: wardag.as@gmail.com
License: MIT
Download-URL: https://github.com/SamirWardak/sendmessageunictelecome
Platform: UNKNOWN
